eforge/__init__.py
eforge-0.0.0.dist-info/METADATA
eforge-0.0.0.dist-info/WHEEL
eforge-0.0.0.dist-info/RECORD
