Metadata-Version: 2.1
Name: eforge
Version: 0.0.0
Summary: 
Author: altar31
Author-email: damien.sicard31@gmail.com
Requires-Python: >=3.10,<4.0
Classifier: Programming Language :: Python :: 3
Classifier: Programming Language :: Python :: 3.10
Classifier: Programming Language :: Python :: 3.11
Requires-Dist: bokeh (>=3.1.0,<4.0.0)
Requires-Dist: matplotlib (>=3.7.1,<4.0.0)
Requires-Dist: numpy (>=1.24.2,<2.0.0)
Requires-Dist: streamlit (>=1.21.0,<2.0.0)
